algo_feature_discretizer/__init__.py
algo_feature_discretizer/feature_discretizer.py
algo_feature_discretizer/grid_search_xgb.py
algo_feature_discretizer/mean_encoder.py
algo_feature_discretizer/stepwise_regressor.py
algo_feature_discretizer/utils.py
scorecardzxh/__init__.py
scorecardzxh/feature_discretizer.py
scorecardzxh/grid_search_xgb.py
scorecardzxh/mean_encoder.py
scorecardzxh/stepwise_regressor.py
scorecardzxh/utils.py
scorecardzxh-0.0.5.dist-info/LICENSE
scorecardzxh-0.0.5.dist-info/METADATA
scorecardzxh-0.0.5.dist-info/WHEEL
scorecardzxh-0.0.5.dist-info/top_level.txt
scorecardzxh-0.0.5.dist-info/RECORD
