Metadata-Version: 2.1
Name: scorecardzxh
Version: 0.0.5
Summary: scorecard modeling tools
Home-page: https://github.com/zhuxiaohai/algo_scorecard_zxh.git
Author: ZXH
Author-email: zhuxiaohai_sast@163.com
License: UNKNOWN
Platform: UNKNOWN
Classifier: Programming Language :: Python :: 3
Classifier: License :: OSI Approved :: MIT License
Classifier: Operating System :: OS Independent
Requires-Python: >=3.6
Requires-Dist: bayesian-optimization (==1.2.0)
